testbook/__init__.py
testbook/_version.py
testbook/client.py
testbook/exceptions.py
testbook/reference.py
testbook/testbook.py
testbook/testbooknode.py
testbook/translators.py
testbook/utils.py
ud_testbook-0.0.4.dist-info/LICENSE
ud_testbook-0.0.4.dist-info/METADATA
ud_testbook-0.0.4.dist-info/WHEEL
ud_testbook-0.0.4.dist-info/top_level.txt
ud_testbook-0.0.4.dist-info/RECORD
